beacon/__init__.py
beacon/cli.py
beacon/config.py
beacon/models.py
beacon/parsers.py
beacon/py.typed
beacon/runner.py
beacon/tuner.py
beacon/chunkers/__init__.py
beacon/chunkers/base.py
beacon/chunkers/fixed.py
beacon/chunkers/recursive.py
beacon/chunkers/registry.py
beacon/chunkers/semantic.py
beacon/chunkers/sentence.py
beacon/embeddings/__init__.py
beacon/embeddings/generator.py
beacon/indexers/__init__.py
beacon/indexers/faiss_index.py
beacon/metrics/__init__.py
beacon/metrics/evaluator.py
beacon/reporters/__init__.py
beacon/reporters/html.py
beacon_eval-0.1.0.dist-info/METADATA
beacon_eval-0.1.0.dist-info/WHEEL
beacon_eval-0.1.0.dist-info/entry_points.txt
beacon_eval-0.1.0.dist-info/licenses/LICENSE
beacon_eval-0.1.0.dist-info/RECORD
