Metadata-Version: 2.4
Name: beacon-eval
Version: 0.1.0
Summary: A benchmarking toolkit that evaluates and compares RAG chunking strategies against your actual queries to find the optimal configuration
Project-URL: Homepage, https://github.com/en-yao/beacon-eval
Project-URL: Documentation, https://github.com/en-yao/beacon-eval#readme
Project-URL: Repository, https://github.com/en-yao/beacon-eval
Project-URL: Issues, https://github.com/en-yao/beacon-eval/issues
Author: Beacon Contributors
License: MIT License
License-File: LICENSE
Keywords: benchmark,chunking,embeddings,evaluation,llm,rag,retrieval,vector-search
Classifier: Development Status :: 3 - Alpha
Classifier: Environment :: Console
Classifier: Intended Audience :: Developers
Classifier: Intended Audience :: Science/Research
Classifier: License :: OSI Approved :: MIT License
Classifier: Operating System :: OS Independent
Classifier: Programming Language :: Python :: 3
Classifier: Programming Language :: Python :: 3.11
Classifier: Programming Language :: Python :: 3.12
Classifier: Topic :: Scientific/Engineering :: Artificial Intelligence
Classifier: Topic :: Text Processing :: Indexing
Requires-Python: >=3.11
Requires-Dist: faiss-cpu>=1.7.0
Requires-Dist: jinja2>=3.0.0
Requires-Dist: numpy>=1.24.0
Requires-Dist: pandas>=2.0.0
Requires-Dist: plotly>=5.0.0
Requires-Dist: pypdf>=3.0.0
Requires-Dist: python-docx>=0.8.0
Requires-Dist: pyyaml>=6.0
Requires-Dist: rich>=13.0.0
Requires-Dist: sentence-transformers>=2.2.0
Requires-Dist: tiktoken>=0.5.0
Requires-Dist: tqdm>=4.65.0
Requires-Dist: typer>=0.9.0
Provides-Extra: dev
Requires-Dist: hypothesis>=6.0.0; extra == 'dev'
Requires-Dist: mypy>=1.0.0; extra == 'dev'
Requires-Dist: pytest-cov>=4.0.0; extra == 'dev'
Requires-Dist: pytest>=7.0.0; extra == 'dev'
Requires-Dist: ruff>=0.1.0; extra == 'dev'
Requires-Dist: types-pyyaml>=6.0.0; extra == 'dev'
Requires-Dist: types-tqdm>=4.0.0; extra == 'dev'
Provides-Extra: full
Requires-Dist: hypothesis>=6.0.0; extra == 'full'
Requires-Dist: mypy>=1.0.0; extra == 'full'
Requires-Dist: optuna>=3.0.0; extra == 'full'
Requires-Dist: pytest-cov>=4.0.0; extra == 'full'
Requires-Dist: pytest>=7.0.0; extra == 'full'
Requires-Dist: ruff>=0.1.0; extra == 'full'
Requires-Dist: types-pyyaml>=6.0.0; extra == 'full'
Requires-Dist: types-tqdm>=4.0.0; extra == 'full'
Provides-Extra: optuna
Requires-Dist: optuna>=3.0.0; extra == 'optuna'
